sails_sdk/__init__.py
sails_sdk-0.1.0.dist-info/licenses/LICENSE
sails_sdk-0.1.0.dist-info/METADATA
sails_sdk-0.1.0.dist-info/WHEEL
sails_sdk-0.1.0.dist-info/top_level.txt
sails_sdk-0.1.0.dist-info/RECORD
