Metadata-Version: 2.4
Name: sails-sdk
Version: 0.1.0
Summary: Python client for the Sails Developer API
Author: Sails AI
License: MIT
Classifier: Development Status :: 3 - Alpha
Classifier: Intended Audience :: Developers
Classifier: License :: OSI Approved :: MIT License
Classifier: Operating System :: OS Independent
Classifier: Programming Language :: Python :: 3
Classifier: Programming Language :: Python :: 3.7
Classifier: Programming Language :: Python :: 3.8
Classifier: Programming Language :: Python :: 3.9
Classifier: Programming Language :: Python :: 3.10
Classifier: Programming Language :: Python :: 3.11
Classifier: Programming Language :: Python :: 3.12
Classifier: Topic :: Software Development :: Libraries
Requires-Python: >=3.7
License-File: LICENSE
Requires-Dist: requests>=2.25.0
Dynamic: author
Dynamic: classifier
Dynamic: description
Dynamic: description-content-type
Dynamic: license
Dynamic: license-file
Dynamic: requires-dist
Dynamic: requires-python
Dynamic: summary
